{
    "preamble": {
        "program": "lime$_{dl}$",
        "prog_args": "lime$_{dl}$",
        "prog_alias": "lime$_{dl}$",
        "benchmark": null
    },
    "stats": {
        "IF Mcv = (-inf..82.17] AND Alkphos = (60.67..73.5] AND Sgpt = (29.0..40.0] AND Sgot = (16.67..24.33] AND Gammagt = (71.0..113.0] AND Drinks = (1.5..4.0] THEN target = 2": {
            "status": true,
            "expl": [],
            "minsize": 0,
            "exprtime": 763.439
        },
        "IF Mcv = (-inf..82.17] AND Alkphos = (73.5..86.33] AND Sgpt = (29.0..40.0] AND Sgot = (24.33..32.0] AND Gammagt = (36.0..52.5] AND Drinks = (-inf..1.5] THEN target = 2": {
            "status": true,
            "expl": [],
            "minsize": 0,
            "exprtime": 762.6299999999997
        },
        "IF Mcv = (82.17..86.33] AND Alkphos = (101.17..+inf) AND Sgpt = (29.0..40.0] AND Sgot = (24.33..32.0] AND Gammagt = (-inf..20.5] AND Drinks = (-inf..1.5] THEN target = 1": {
            "status": true,
            "expl": [
                "Mcv",
                "Alkphos",
                "Gammagt",
                "Drinks"
            ],
            "minsize": 4,
            "exprtime": 757.6519999999998
        },
        "IF Mcv = (82.17..86.33] AND Alkphos = (47.83..60.67] AND Sgpt = (-inf..18.0] AND Sgot = (16.67..24.33] AND Gammagt = (20.5..36.0] AND Drinks = (-inf..1.5] THEN target = 2": {
            "status": true,
            "expl": [],
            "minsize": 0,
            "exprtime": 755.8999999999995
        },
        "IF Mcv = (82.17..86.33] AND Alkphos = (47.83..60.67] AND Sgpt = (18.0..29.0] AND Sgot = (16.67..24.33] AND Gammagt = (20.5..36.0] AND Drinks = (-inf..1.5] THEN target = 2": {
            "status": true,
            "expl": [],
            "minsize": 0,
            "exprtime": 755.5569999999996
        },
        "IF Mcv = (82.17..86.33] AND Alkphos = (47.83..60.67] AND Sgpt = (18.0..29.0] AND Sgot = (16.67..24.33] AND Gammagt = (20.5..36.0] AND Drinks = (1.5..4.0] THEN target = 2": {
            "status": true,
            "expl": [],
            "minsize": 0,
            "exprtime": 752.6019999999995
        },
        "IF Mcv = (82.17..86.33] AND Alkphos = (47.83..60.67] AND Sgpt = (18.0..29.0] AND Sgot = (24.33..32.0] AND Gammagt = (-inf..20.5] AND Drinks = (-inf..1.5] THEN target = 1": {
            "status": true,
            "expl": [
                "Mcv",
                "Alkphos",
                "Sgpt",
                "Gammagt",
                "Drinks"
            ],
            "minsize": 5,
            "exprtime": 737.4049999999999
        },
        "IF Mcv = (82.17..86.33] AND Alkphos = (47.83..60.67] AND Sgpt = (29.0..40.0] AND Sgot = (24.33..32.0] AND Gammagt = (52.5..71.0] AND Drinks = (-inf..1.5] THEN target = 2": {
            "status": true,
            "expl": [],
            "minsize": 0,
            "exprtime": 747.6530000000006
        },
        "IF Mcv = (82.17..86.33] AND Alkphos = (60.67..73.5] AND Sgpt = (40.0..53.0] AND Sgot = (24.33..32.0] AND Gammagt = (36.0..52.5] AND Drinks = (1.5..4.0] THEN target = 2": {
            "status": true,
            "expl": [],
            "minsize": 0,
            "exprtime": 747.477
        },
        "IF Mcv = (82.17..86.33] AND Alkphos = (73.5..86.33] AND Sgpt = (18.0..29.0] AND Sgot = (24.33..32.0] AND Gammagt = (20.5..36.0] AND Drinks = (-inf..1.5] THEN target = 1": {
            "status": true,
            "expl": [
                "Mcv",
                "Sgpt",
                "Drinks"
            ],
            "minsize": 3,
            "exprtime": 741.6689999999999
        },
        "IF Mcv = (82.17..86.33] AND Alkphos = (86.33..101.17] AND Sgpt = (29.0..40.0] AND Sgot = (16.67..24.33] AND Gammagt = (20.5..36.0] AND Drinks = (6.5..9.0] THEN target = 1": {
            "status": true,
            "expl": [
                "Mcv",
                "Sgot"
            ],
            "minsize": 2,
            "exprtime": 748.0619999999991
        },
        "IF Mcv = (86.33..90.5] AND Alkphos = (-inf..47.83] AND Sgpt = (-inf..18.0] AND Sgot = (-inf..16.67] AND Gammagt = (-inf..20.5] AND Drinks = (4.0..6.5] THEN target = 2": {
            "status": true,
            "expl": [],
            "minsize": 0,
            "exprtime": 741.7829999999999
        },
        "IF Mcv = (86.33..90.5] AND Alkphos = (-inf..47.83] AND Sgpt = (-inf..18.0] AND Sgot = (32.0..40.33] AND Gammagt = (52.5..71.0] AND Drinks = (1.5..4.0] THEN target = 1": {
            "status": true,
            "expl": [
                "Mcv",
                "Alkphos",
                "Sgpt",
                "Drinks"
            ],
            "minsize": 4,
            "exprtime": 746.7669999999985
        },
        "IF Mcv = (86.33..90.5] AND Alkphos = (-inf..47.83] AND Sgpt = (18.0..29.0] AND Sgot = (-inf..16.67] AND Gammagt = (-inf..20.5] AND Drinks = (-inf..1.5] THEN target = 2": {
            "status": true,
            "expl": [],
            "minsize": 0,
            "exprtime": 739.6329999999996
        },
        "IF Mcv = (86.33..90.5] AND Alkphos = (47.83..60.67] AND Sgpt = (-inf..18.0] AND Sgot = (16.67..24.33] AND Gammagt = (-inf..20.5] AND Drinks = (-inf..1.5] THEN target = 2": {
            "status": true,
            "expl": [],
            "minsize": 0,
            "exprtime": 722.9720000000004
        },
        "IF Mcv = (86.33..90.5] AND Alkphos = (47.83..60.67] AND Sgpt = (18.0..29.0] AND Sgot = (16.67..24.33] AND Gammagt = (-inf..20.5] AND Drinks = (-inf..1.5] THEN target = 1": {
            "status": true,
            "expl": [
                "Mcv",
                "Alkphos",
                "Sgpt",
                "Sgot",
                "Gammagt",
                "Drinks"
            ],
            "minsize": 6,
            "exprtime": 717.8939999999993
        },
        "IF Mcv = (86.33..90.5] AND Alkphos = (47.83..60.67] AND Sgpt = (18.0..29.0] AND Sgot = (16.67..24.33] AND Gammagt = (20.5..36.0] AND Drinks = (1.5..4.0] THEN target = 2": {
            "status": true,
            "expl": [],
            "minsize": 0,
            "exprtime": 711.8200000000012
        },
        "IF Mcv = (86.33..90.5] AND Alkphos = (47.83..60.67] AND Sgpt = (18.0..29.0] AND Sgot = (16.67..24.33] AND Gammagt = (52.5..71.0] AND Drinks = (6.5..9.0] THEN target = 2": {
            "status": true,
            "expl": [],
            "minsize": 0,
            "exprtime": 709.1209999999996
        },
        "IF Mcv = (86.33..90.5] AND Alkphos = (47.83..60.67] AND Sgpt = (29.0..40.0] AND Sgot = (16.67..24.33] AND Gammagt = (-inf..20.5] AND Drinks = (1.5..4.0] THEN target = 2": {
            "status": true,
            "expl": [],
            "minsize": 0,
            "exprtime": 713.5709999999999
        },
        "IF Mcv = (86.33..90.5] AND Alkphos = (60.67..73.5] AND Sgpt = (-inf..18.0] AND Sgot = (16.67..24.33] AND Gammagt = (-inf..20.5] AND Drinks = (-inf..1.5] THEN target = 2": {
            "status": true,
            "expl": [],
            "minsize": 0,
            "exprtime": 721.5509999999998
        },
        "IF Mcv = (86.33..90.5] AND Alkphos = (60.67..73.5] AND Sgpt = (-inf..18.0] AND Sgot = (16.67..24.33] AND Gammagt = (-inf..20.5] AND Drinks = (4.0..6.5] THEN target = 2": {
            "status": true,
            "expl": [],
            "minsize": 0,
            "exprtime": 710.7929999999989
        },
        "IF Mcv = (86.33..90.5] AND Alkphos = (60.67..73.5] AND Sgpt = (-inf..18.0] AND Sgot = (24.33..32.0] AND Gammagt = (20.5..36.0] AND Drinks = (4.0..6.5] THEN target = 2": {
            "status": true,
            "expl": [],
            "minsize": 0,
            "exprtime": 705.0059999999974
        },
        "IF Mcv = (86.33..90.5] AND Alkphos = (60.67..73.5] AND Sgpt = (18.0..29.0] AND Sgot = (16.67..24.33] AND Gammagt = (-inf..20.5] AND Drinks = (-inf..1.5] THEN target = 1": {
            "status": true,
            "expl": [
                "Mcv",
                "Sgpt",
                "Sgot",
                "Gammagt",
                "Drinks"
            ],
            "minsize": 5,
            "exprtime": 722.1859999999971
        },
        "IF Mcv = (86.33..90.5] AND Alkphos = (60.67..73.5] AND Sgpt = (18.0..29.0] AND Sgot = (16.67..24.33] AND Gammagt = (52.5..71.0] AND Drinks = (1.5..4.0] THEN target = 2": {
            "status": true,
            "expl": [],
            "minsize": 0,
            "exprtime": 713.201999999999
        },
        "IF Mcv = (86.33..90.5] AND Alkphos = (60.67..73.5] AND Sgpt = (29.0..40.0] AND Sgot = (16.67..24.33] AND Gammagt = (20.5..36.0] AND Drinks = (1.5..4.0] THEN target = 1": {
            "status": true,
            "expl": [
                "Mcv",
                "Sgot",
                "Drinks"
            ],
            "minsize": 3,
            "exprtime": 718.433000000001
        },
        "IF Mcv = (86.33..90.5] AND Alkphos = (60.67..73.5] AND Sgpt = (76.0..+inf) AND Sgot = (32.0..40.33] AND Gammagt = (113.0..+inf) AND Drinks = (6.5..9.0] THEN target = 2": {
            "status": true,
            "expl": [],
            "minsize": 0,
            "exprtime": 715.9800000000018
        },
        "IF Mcv = (86.33..90.5] AND Alkphos = (73.5..86.33] AND Sgpt = (-inf..18.0] AND Sgot = (-inf..16.67] AND Gammagt = (20.5..36.0] AND Drinks = (-inf..1.5] THEN target = 2": {
            "status": true,
            "expl": [],
            "minsize": 0,
            "exprtime": 719.570000000001
        },
        "IF Mcv = (86.33..90.5] AND Alkphos = (73.5..86.33] AND Sgpt = (18.0..29.0] AND Sgot = (24.33..32.0] AND Gammagt = (-inf..20.5] AND Drinks = (1.5..4.0] THEN target = 1": {
            "status": true,
            "expl": [
                "Mcv",
                "Sgpt",
                "Gammagt",
                "Drinks"
            ],
            "minsize": 4,
            "exprtime": 714.106000000001
        },
        "IF Mcv = (86.33..90.5] AND Alkphos = (73.5..86.33] AND Sgpt = (18.0..29.0] AND Sgot = (51.67..+inf) AND Gammagt = (-inf..20.5] AND Drinks = (1.5..4.0] THEN target = 2": {
            "status": true,
            "expl": [],
            "minsize": 0,
            "exprtime": 709.1229999999982
        },
        "IF Mcv = (86.33..90.5] AND Alkphos = (73.5..86.33] AND Sgpt = (29.0..40.0] AND Sgot = (16.67..24.33] AND Gammagt = (36.0..52.5] AND Drinks = (4.0..6.5] THEN target = 2": {
            "status": true,
            "expl": [],
            "minsize": 0,
            "exprtime": 715.6309999999984
        },
        "IF Mcv = (86.33..90.5] AND Alkphos = (73.5..86.33] AND Sgpt = (29.0..40.0] AND Sgot = (24.33..32.0] AND Gammagt = (-inf..20.5] AND Drinks = (-inf..1.5] THEN target = 1": {
            "status": true,
            "expl": [
                "Mcv",
                "Gammagt",
                "Drinks"
            ],
            "minsize": 3,
            "exprtime": 715.9219999999991
        },
        "IF Mcv = (86.33..90.5] AND Alkphos = (86.33..101.17] AND Sgpt = (18.0..29.0] AND Sgot = (16.67..24.33] AND Gammagt = (36.0..52.5] AND Drinks = (-inf..1.5] THEN target = 2": {
            "status": true,
            "expl": [],
            "minsize": 0,
            "exprtime": 710.0039999999979
        },
        "IF Mcv = (86.33..90.5] AND Alkphos = (86.33..101.17] AND Sgpt = (18.0..29.0] AND Sgot = (24.33..32.0] AND Gammagt = (-inf..20.5] AND Drinks = (-inf..1.5] THEN target = 1": {
            "status": true,
            "expl": [
                "Mcv",
                "Sgpt",
                "Gammagt",
                "Drinks"
            ],
            "minsize": 4,
            "exprtime": 711.8859999999997
        },
        "IF Mcv = (86.33..90.5] AND Alkphos = (86.33..101.17] AND Sgpt = (40.0..53.0] AND Sgot = (24.33..32.0] AND Gammagt = (113.0..+inf) AND Drinks = (1.5..4.0] THEN target = 2": {
            "status": true,
            "expl": [],
            "minsize": 0,
            "exprtime": 712.2630000000001
        },
        "IF Mcv = (90.5..94.67] AND Alkphos = (101.17..+inf) AND Sgpt = (-inf..18.0] AND Sgot = (32.0..40.33] AND Gammagt = (-inf..20.5] AND Drinks = (-inf..1.5] THEN target = 1": {
            "status": true,
            "expl": [
                "Alkphos",
                "Sgpt",
                "Gammagt",
                "Drinks"
            ],
            "minsize": 4,
            "exprtime": 710.014000000001
        },
        "IF Mcv = (90.5..94.67] AND Alkphos = (101.17..+inf) AND Sgpt = (29.0..40.0] AND Sgot = (-inf..16.67] AND Gammagt = (-inf..20.5] AND Drinks = (1.5..4.0] THEN target = 1": {
            "status": true,
            "expl": [
                "Alkphos",
                "Sgot",
                "Gammagt",
                "Drinks"
            ],
            "minsize": 4,
            "exprtime": 710.4970000000002
        },
        "IF Mcv = (90.5..94.67] AND Alkphos = (101.17..+inf) AND Sgpt = (40.0..53.0] AND Sgot = (16.67..24.33] AND Gammagt = (36.0..52.5] AND Drinks = (9.0..13.5] THEN target = 2": {
            "status": true,
            "expl": [],
            "minsize": 0,
            "exprtime": 720.6130000000002
        },
        "IF Mcv = (90.5..94.67] AND Alkphos = (101.17..+inf) AND Sgpt = (40.0..53.0] AND Sgot = (32.0..40.33] AND Gammagt = (71.0..113.0] AND Drinks = (9.0..13.5] THEN target = 1": {
            "status": true,
            "expl": [
                "Alkphos"
            ],
            "minsize": 1,
            "exprtime": 732.4699999999993
        },
        "IF Mcv = (90.5..94.67] AND Alkphos = (47.83..60.67] AND Sgpt = (-inf..18.0] AND Sgot = (24.33..32.0] AND Gammagt = (-inf..20.5] AND Drinks = (4.0..6.5] THEN target = 2": {
            "status": true,
            "expl": [],
            "minsize": 0,
            "exprtime": 730.5849999999978
        },
        "IF Mcv = (90.5..94.67] AND Alkphos = (47.83..60.67] AND Sgpt = (18.0..29.0] AND Sgot = (-inf..16.67] AND Gammagt = (-inf..20.5] AND Drinks = (-inf..1.5] THEN target = 1": {
            "status": true,
            "expl": [
                "Alkphos",
                "Sgpt",
                "Sgot",
                "Gammagt",
                "Drinks"
            ],
            "minsize": 5,
            "exprtime": 734.8040000000004
        },
        "IF Mcv = (90.5..94.67] AND Alkphos = (60.67..73.5] AND Sgpt = (-inf..18.0] AND Sgot = (-inf..16.67] AND Gammagt = (71.0..113.0] AND Drinks = (1.5..4.0] THEN target = 2": {
            "status": true,
            "expl": [],
            "minsize": 0,
            "exprtime": 734.2549999999974
        },
        "IF Mcv = (90.5..94.67] AND Alkphos = (60.67..73.5] AND Sgpt = (-inf..18.0] AND Sgot = (16.67..24.33] AND Gammagt = (-inf..20.5] AND Drinks = (1.5..4.0] THEN target = 2": {
            "status": true,
            "expl": [],
            "minsize": 0,
            "exprtime": 744.0770000000008
        },
        "IF Mcv = (90.5..94.67] AND Alkphos = (60.67..73.5] AND Sgpt = (-inf..18.0] AND Sgot = (24.33..32.0] AND Gammagt = (-inf..20.5] AND Drinks = (1.5..4.0] THEN target = 2": {
            "status": true,
            "expl": [],
            "minsize": 0,
            "exprtime": 744.290999999997
        },
        "IF Mcv = (90.5..94.67] AND Alkphos = (60.67..73.5] AND Sgpt = (18.0..29.0] AND Sgot = (-inf..16.67] AND Gammagt = (-inf..20.5] AND Drinks = (-inf..1.5] THEN target = 1": {
            "status": true,
            "expl": [
                "Sgpt",
                "Sgot",
                "Gammagt",
                "Drinks"
            ],
            "minsize": 4,
            "exprtime": 741.8079999999989
        },
        "IF Mcv = (90.5..94.67] AND Alkphos = (60.67..73.5] AND Sgpt = (18.0..29.0] AND Sgot = (-inf..16.67] AND Gammagt = (20.5..36.0] AND Drinks = (-inf..1.5] THEN target = 1": {
            "status": true,
            "expl": [
                "Sgpt",
                "Sgot",
                "Drinks"
            ],
            "minsize": 3,
            "exprtime": 734.9779999999981
        },
        "IF Mcv = (90.5..94.67] AND Alkphos = (60.67..73.5] AND Sgpt = (18.0..29.0] AND Sgot = (16.67..24.33] AND Gammagt = (20.5..36.0] AND Drinks = (1.5..4.0] THEN target = 2": {
            "status": true,
            "expl": [],
            "minsize": 0,
            "exprtime": 713.6270000000025
        },
        "IF Mcv = (90.5..94.67] AND Alkphos = (60.67..73.5] AND Sgpt = (18.0..29.0] AND Sgot = (24.33..32.0] AND Gammagt = (-inf..20.5] AND Drinks = (4.0..6.5] THEN target = 1": {
            "status": true,
            "expl": [
                "Sgpt",
                "Gammagt"
            ],
            "minsize": 2,
            "exprtime": 720.6569999999956
        },
        "IF Mcv = (90.5..94.67] AND Alkphos = (73.5..86.33] AND Sgpt = (18.0..29.0] AND Sgot = (16.67..24.33] AND Gammagt = (36.0..52.5] AND Drinks = (4.0..6.5] THEN target = 2": {
            "status": true,
            "expl": [],
            "minsize": 0,
            "exprtime": 720.4349999999948
        },
        "IF Mcv = (90.5..94.67] AND Alkphos = (73.5..86.33] AND Sgpt = (18.0..29.0] AND Sgot = (24.33..32.0] AND Gammagt = (-inf..20.5] AND Drinks = (-inf..1.5] THEN target = 2": {
            "status": true,
            "expl": [],
            "minsize": 0,
            "exprtime": 712.9690000000011
        },
        "IF Mcv = (90.5..94.67] AND Alkphos = (73.5..86.33] AND Sgpt = (29.0..40.0] AND Sgot = (16.67..24.33] AND Gammagt = (20.5..36.0] AND Drinks = (-inf..1.5] THEN target = 1": {
            "status": true,
            "expl": [
                "Sgot",
                "Drinks"
            ],
            "minsize": 2,
            "exprtime": 713.4709999999984
        },
        "IF Mcv = (90.5..94.67] AND Alkphos = (73.5..86.33] AND Sgpt = (53.0..76.0] AND Sgot = (40.33..51.67] AND Gammagt = (52.5..71.0] AND Drinks = (6.5..9.0] THEN target = 2": {
            "status": true,
            "expl": [],
            "minsize": 0,
            "exprtime": 716.228000000001
        },
        "IF Mcv = (90.5..94.67] AND Alkphos = (73.5..86.33] AND Sgpt = (76.0..+inf) AND Sgot = (32.0..40.33] AND Gammagt = (113.0..+inf) AND Drinks = (13.5..+inf) THEN target = 1": {
            "status": true,
            "expl": [
                "Gammagt"
            ],
            "minsize": 1,
            "exprtime": 724.7860000000016
        },
        "IF Mcv = (90.5..94.67] AND Alkphos = (86.33..101.17] AND Sgpt = (-inf..18.0] AND Sgot = (16.67..24.33] AND Gammagt = (-inf..20.5] AND Drinks = (6.5..9.0] THEN target = 2": {
            "status": true,
            "expl": [],
            "minsize": 0,
            "exprtime": 716.0730000000015
        },
        "IF Mcv = (90.5..94.67] AND Alkphos = (86.33..101.17] AND Sgpt = (-inf..18.0] AND Sgot = (16.67..24.33] AND Gammagt = (20.5..36.0] AND Drinks = (1.5..4.0] THEN target = 2": {
            "status": true,
            "expl": [],
            "minsize": 0,
            "exprtime": 714.7720000000036
        },
        "IF Mcv = (90.5..94.67] AND Alkphos = (86.33..101.17] AND Sgpt = (29.0..40.0] AND Sgot = (32.0..40.33] AND Gammagt = (36.0..52.5] AND Drinks = (4.0..6.5] THEN target = 2": {
            "status": true,
            "expl": [],
            "minsize": 0,
            "exprtime": 712.9210000000014
        },
        "IF Mcv = (94.67..98.83] AND Alkphos = (-inf..47.83] AND Sgpt = (29.0..40.0] AND Sgot = (16.67..24.33] AND Gammagt = (-inf..20.5] AND Drinks = (4.0..6.5] THEN target = 2": {
            "status": true,
            "expl": [],
            "minsize": 0,
            "exprtime": 715.6889999999976
        },
        "IF Mcv = (94.67..98.83] AND Alkphos = (-inf..47.83] AND Sgpt = (29.0..40.0] AND Sgot = (16.67..24.33] AND Gammagt = (52.5..71.0] AND Drinks = (4.0..6.5] THEN target = 2": {
            "status": true,
            "expl": [],
            "minsize": 0,
            "exprtime": 716.9409999999984
        },
        "IF Mcv = (94.67..98.83] AND Alkphos = (47.83..60.67] AND Sgpt = (18.0..29.0] AND Sgot = (16.67..24.33] AND Gammagt = (20.5..36.0] AND Drinks = (4.0..6.5] THEN target = 2": {
            "status": true,
            "expl": [],
            "minsize": 0,
            "exprtime": 716.1539999999959
        },
        "IF Mcv = (94.67..98.83] AND Alkphos = (60.67..73.5] AND Sgpt = (40.0..53.0] AND Sgot = (40.33..51.67] AND Gammagt = (113.0..+inf) AND Drinks = (9.0..13.5] THEN target = 1": {
            "status": true,
            "expl": [
                "Gammagt"
            ],
            "minsize": 1,
            "exprtime": 715.6079999999961
        },
        "IF Mcv = (94.67..98.83] AND Alkphos = (86.33..101.17] AND Sgpt = (18.0..29.0] AND Sgot = (24.33..32.0] AND Gammagt = (36.0..52.5] AND Drinks = (4.0..6.5] THEN target = 2": {
            "status": true,
            "expl": [],
            "minsize": 0,
            "exprtime": 723.4940000000023
        },
        "IF Mcv = (94.67..98.83] AND Alkphos = (86.33..101.17] AND Sgpt = (18.0..29.0] AND Sgot = (24.33..32.0] AND Gammagt = (36.0..52.5] AND Drinks = (9.0..13.5] THEN target = 2": {
            "status": true,
            "expl": [],
            "minsize": 0,
            "exprtime": 713.6539999999982
        },
        "IF Mcv = (94.67..98.83] AND Alkphos = (86.33..101.17] AND Sgpt = (29.0..40.0] AND Sgot = (24.33..32.0] AND Gammagt = (20.5..36.0] AND Drinks = (4.0..6.5] THEN target = 2": {
            "status": true,
            "expl": [],
            "minsize": 0,
            "exprtime": 718.2150000000007
        },
        "IF Mcv = (98.83..+inf) AND Alkphos = (-inf..47.83] AND Sgpt = (-inf..18.0] AND Sgot = (16.67..24.33] AND Gammagt = (36.0..52.5] AND Drinks = (4.0..6.5] THEN target = 1": {
            "status": true,
            "expl": [
                "Alkphos",
                "Sgpt",
                "Sgot"
            ],
            "minsize": 3,
            "exprtime": 724.9259999999964
        },
        "IF Mcv = (98.83..+inf) AND Alkphos = (73.5..86.33] AND Sgpt = (18.0..29.0] AND Sgot = (24.33..32.0] AND Gammagt = (-inf..20.5] AND Drinks = (-inf..1.5] THEN target = 2": {
            "status": true,
            "expl": [],
            "minsize": 0,
            "exprtime": 710.0039999999979
        }
    }
}