{
    "preamble": {
        "program": "anchor$_{dl}$",
        "prog_args": "anchor$_{dl}$",
        "prog_alias": "anchor$_{dl}$",
        "benchmark": null
    },
    "stats": {
        "IF age = (-inf..40.67] AND sex = 0 AND cp = 2 AND trestbps = (134.0..146.0] AND chol = (219.33..245.5] AND fbs = 0 AND restecg = 1 AND thalach = (146.0..161.0] AND exang = 0 AND oldpeak = (-inf..0.65] AND slope = 1 AND ca = 0 AND thal = 2 THEN target = 1": {
            "status": true,
            "expl": [
                "cp",
                "age"
            ],
            "minsize": 2,
            "exprtime": 268.71500000000003
        },
        "IF age = (-inf..40.67] AND sex = 1 AND cp = 0 AND trestbps = (-inf..110.0] AND chol = (-inf..192.17] AND fbs = 0 AND restecg = 0 AND thalach = (-inf..114.0] AND exang = 1 AND oldpeak = (1.3..2.05] AND slope = 1 AND ca = 0 AND thal = 3 THEN target = 0": {
            "status": true,
            "expl": [
                "thalach",
                "thal",
                "cp",
                "age"
            ],
            "minsize": 4,
            "exprtime": 324.2130000000003
        },
        "IF age = (-inf..40.67] AND sex = 1 AND cp = 0 AND trestbps = (123.0..134.0] AND chol = (272.33..306.83] AND fbs = 0 AND restecg = 0 AND thalach = (146.0..161.0] AND exang = 1 AND oldpeak = (-inf..0.65] AND slope = 2 AND ca = 0 AND thal = 3 THEN target = 0": {
            "status": true,
            "expl": [
                "cp",
                "thal",
                "age",
                "thalach"
            ],
            "minsize": 4,
            "exprtime": 529.9879999999999
        },
        "IF age = (-inf..40.67] AND sex = 1 AND cp = 0 AND trestbps = (146.0..164.0] AND chol = (219.33..245.5] AND fbs = 0 AND restecg = 1 AND thalach = (177.0..+inf) AND exang = 0 AND oldpeak = (-inf..0.65] AND slope = 2 AND ca = 0 AND thal = 3 THEN target = 1": {
            "status": true,
            "expl": [
                "thalach"
            ],
            "minsize": 1,
            "exprtime": 106.46200000000006
        },
        "IF age = (-inf..40.67] AND sex = 1 AND cp = 2 AND trestbps = (123.0..134.0] AND chol = (245.5..272.33] AND fbs = 0 AND restecg = 1 AND thalach = (177.0..+inf) AND exang = 0 AND oldpeak = (2.8..3.55] AND slope = 0 AND ca = 0 AND thal = 2 THEN target = 1": {
            "status": true,
            "expl": [
                "thalach"
            ],
            "minsize": 1,
            "exprtime": 74.10099999999974
        },
        "IF age = (-inf..40.67] AND sex = 1 AND cp = 3 AND trestbps = (134.0..146.0] AND chol = (192.17..219.33] AND fbs = 0 AND restecg = 1 AND thalach = (177.0..+inf) AND exang = 1 AND oldpeak = (1.3..2.05] AND slope = 2 AND ca = 0 AND thal = 3 THEN target = 1": {
            "status": true,
            "expl": [
                "thalach"
            ],
            "minsize": 1,
            "exprtime": 105.52699999999993
        },
        "IF age = (40.67..47.33] AND sex = 0 AND cp = 0 AND trestbps = (134.0..146.0] AND chol = (219.33..245.5] AND fbs = 0 AND restecg = 0 AND thalach = (146.0..161.0] AND exang = 1 AND oldpeak = (-inf..0.65] AND slope = 1 AND ca = 0 AND thal = 2 THEN target = 1": {
            "status": true,
            "expl": [
                "ca",
                "oldpeak",
                "chol"
            ],
            "minsize": 3,
            "exprtime": 574.0840000000001
        },
        "IF age = (40.67..47.33] AND sex = 0 AND cp = 1 AND trestbps = (-inf..110.0] AND chol = (192.17..219.33] AND fbs = 0 AND restecg = 1 AND thalach = (161.0..177.0] AND exang = 0 AND oldpeak = (-inf..0.65] AND slope = 2 AND ca = 0 AND thal = 2 THEN target = 1": {
            "status": true,
            "expl": [
                "sex",
                "thal",
                "ca",
                "trestbps"
            ],
            "minsize": 4,
            "exprtime": 546.9160000000004
        },
        "IF age = (40.67..47.33] AND sex = 0 AND cp = 2 AND trestbps = (110.0..123.0] AND chol = (192.17..219.33] AND fbs = 0 AND restecg = 1 AND thalach = (161.0..177.0] AND exang = 0 AND oldpeak = (-inf..0.65] AND slope = 1 AND ca = 0 AND thal = 2 THEN target = 1": {
            "status": true,
            "expl": [
                "cp",
                "sex",
                "chol"
            ],
            "minsize": 3,
            "exprtime": 257.72300000000035
        },
        "IF age = (40.67..47.33] AND sex = 0 AND cp = 2 AND trestbps = (110.0..123.0] AND chol = (219.33..245.5] AND fbs = 0 AND restecg = 1 AND thalach = (146.0..161.0] AND exang = 0 AND oldpeak = (-inf..0.65] AND slope = 1 AND ca = 1 AND thal = 2 THEN target = 1": {
            "status": true,
            "expl": [
                "cp",
                "thal",
                "sex"
            ],
            "minsize": 3,
            "exprtime": 256.52899999999954
        },
        "IF age = (40.67..47.33] AND sex = 1 AND cp = 0 AND trestbps = (-inf..110.0] AND chol = (192.17..219.33] AND fbs = 0 AND restecg = 0 AND thalach = (161.0..177.0] AND exang = 0 AND oldpeak = (-inf..0.65] AND slope = 2 AND ca = 1 AND thal = 2 THEN target = 1": {
            "status": true,
            "expl": [
                "age",
                "thalach",
                "oldpeak",
                "thal",
                "chol",
                "trestbps",
                "ca",
                "slope"
            ],
            "minsize": 8,
            "exprtime": 1251.8500000000001
        },
        "IF age = (40.67..47.33] AND sex = 1 AND cp = 0 AND trestbps = (123.0..134.0] AND chol = (245.5..272.33] AND fbs = 1 AND restecg = 0 AND thalach = (130.0..146.0] AND exang = 1 AND oldpeak = (-inf..0.65] AND slope = 1 AND ca = 4 AND thal = 3 THEN target = 1": {
            "status": true,
            "expl": [
                "ca"
            ],
            "minsize": 1,
            "exprtime": 94.99600000000008
        },
        "IF age = (40.67..47.33] AND sex = 1 AND cp = 0 AND trestbps = (134.0..146.0] AND chol = (219.33..245.5] AND fbs = 0 AND restecg = 1 AND thalach = (177.0..+inf) AND exang = 0 AND oldpeak = (-inf..0.65] AND slope = 2 AND ca = 0 AND thal = 2 THEN target = 1": {
            "status": true,
            "expl": [
                "thalach"
            ],
            "minsize": 1,
            "exprtime": 73.1730000000006
        },
        "IF age = (40.67..47.33] AND sex = 1 AND cp = 1 AND trestbps = (-inf..110.0] AND chol = (192.17..219.33] AND fbs = 1 AND restecg = 1 AND thalach = (146.0..161.0] AND exang = 0 AND oldpeak = (-inf..0.65] AND slope = 2 AND ca = 0 AND thal = 3 THEN target = 1": {
            "status": true,
            "expl": [
                "ca",
                "cp",
                "age"
            ],
            "minsize": 3,
            "exprtime": 446.6399999999995
        },
        "IF age = (40.67..47.33] AND sex = 1 AND cp = 1 AND trestbps = (-inf..110.0] AND chol = (219.33..245.5] AND fbs = 0 AND restecg = 1 AND thalach = (146.0..161.0] AND exang = 0 AND oldpeak = (-inf..0.65] AND slope = 2 AND ca = 0 AND thal = 2 THEN target = 1": {
            "status": true,
            "expl": [
                "ca",
                "cp",
                "thal"
            ],
            "minsize": 3,
            "exprtime": 383.08000000000055
        },
        "IF age = (40.67..47.33] AND sex = 1 AND cp = 1 AND trestbps = (110.0..123.0] AND chol = (245.5..272.33] AND fbs = 0 AND restecg = 1 AND thalach = (161.0..177.0] AND exang = 0 AND oldpeak = (-inf..0.65] AND slope = 2 AND ca = 0 AND thal = 3 THEN target = 1": {
            "status": true,
            "expl": [
                "ca",
                "oldpeak",
                "trestbps"
            ],
            "minsize": 3,
            "exprtime": 426.914
        },
        "IF age = (40.67..47.33] AND sex = 1 AND cp = 1 AND trestbps = (123.0..134.0] AND chol = (192.17..219.33] AND fbs = 0 AND restecg = 0 AND thalach = (177.0..+inf) AND exang = 0 AND oldpeak = (-inf..0.65] AND slope = 2 AND ca = 0 AND thal = 2 THEN target = 1": {
            "status": true,
            "expl": [
                "thalach"
            ],
            "minsize": 1,
            "exprtime": 126.61299999999986
        },
        "IF age = (40.67..47.33] AND sex = 1 AND cp = 2 AND trestbps = (123.0..134.0] AND chol = (306.83..+inf) AND fbs = 0 AND restecg = 1 AND thalach = (161.0..177.0] AND exang = 0 AND oldpeak = (1.3..2.05] AND slope = 2 AND ca = 1 AND thal = 2 THEN target = 1": {
            "status": true,
            "expl": [
                "cp",
                "thal",
                "oldpeak"
            ],
            "minsize": 3,
            "exprtime": 235.70600000000042
        },
        "IF age = (40.67..47.33] AND sex = 1 AND cp = 3 AND trestbps = (-inf..110.0] AND chol = (245.5..272.33] AND fbs = 0 AND restecg = 1 AND thalach = (130.0..146.0] AND exang = 0 AND oldpeak = (0.65..1.3] AND slope = 1 AND ca = 0 AND thal = 3 THEN target = 1": {
            "status": true,
            "expl": [
                "cp",
                "ca",
                "age",
                "oldpeak"
            ],
            "minsize": 4,
            "exprtime": 235.0279999999998
        },
        "IF age = (47.33..54.0] AND sex = 0 AND cp = 2 AND trestbps = (123.0..134.0] AND chol = (245.5..272.33] AND fbs = 0 AND restecg = 0 AND thalach = (146.0..161.0] AND exang = 0 AND oldpeak = (-inf..0.65] AND slope = 2 AND ca = 0 AND thal = 2 THEN target = 1": {
            "status": true,
            "expl": [
                "cp",
                "sex",
                "age"
            ],
            "minsize": 3,
            "exprtime": 377.834
        },
        "IF age = (47.33..54.0] AND sex = 0 AND cp = 2 AND trestbps = (146.0..164.0] AND chol = (192.17..219.33] AND fbs = 0 AND restecg = 1 AND thalach = (161.0..177.0] AND exang = 0 AND oldpeak = (-inf..0.65] AND slope = 2 AND ca = 1 AND thal = 2 THEN target = 1": {
            "status": true,
            "expl": [
                "cp",
                "thal",
                "sex"
            ],
            "minsize": 3,
            "exprtime": 273.25100000000015
        },
        "IF age = (47.33..54.0] AND sex = 1 AND cp = 0 AND trestbps = (110.0..123.0] AND chol = (219.33..245.5] AND fbs = 0 AND restecg = 0 AND thalach = (177.0..+inf) AND exang = 0 AND oldpeak = (-inf..0.65] AND slope = 2 AND ca = 0 AND thal = 2 THEN target = 1": {
            "status": true,
            "expl": [
                "thalach"
            ],
            "minsize": 1,
            "exprtime": 125.17699999999898
        },
        "IF age = (47.33..54.0] AND sex = 1 AND cp = 0 AND trestbps = (110.0..123.0] AND chol = (272.33..306.83] AND fbs = 0 AND restecg = 0 AND thalach = (114.0..130.0] AND exang = 1 AND oldpeak = (2.8..3.55] AND slope = 1 AND ca = 2 AND thal = 2 THEN target = 0": {
            "status": true,
            "expl": [
                "oldpeak",
                "age",
                "thalach"
            ],
            "minsize": 3,
            "exprtime": 135.98299999999952
        },
        "IF age = (47.33..54.0] AND sex = 1 AND cp = 0 AND trestbps = (134.0..146.0] AND chol = (245.5..272.33] AND fbs = 0 AND restecg = 0 AND thalach = (177.0..+inf) AND exang = 1 AND oldpeak = (-inf..0.65] AND slope = 2 AND ca = 0 AND thal = 2 THEN target = 1": {
            "status": true,
            "expl": [
                "thalach"
            ],
            "minsize": 1,
            "exprtime": 60.93499999999885
        },
        "IF age = (47.33..54.0] AND sex = 1 AND cp = 0 AND trestbps = (134.0..146.0] AND chol = (272.33..306.83] AND fbs = 0 AND restecg = 1 AND thalach = (161.0..177.0] AND exang = 1 AND oldpeak = (1.3..2.05] AND slope = 2 AND ca = 0 AND thal = 3 THEN target = 0": {
            "status": true,
            "expl": [
                "cp",
                "thal",
                "sex",
                "exang",
                "fbs",
                "chol",
                "age",
                "thalach",
                "trestbps"
            ],
            "minsize": 9,
            "exprtime": 1124.512000000001
        },
        "IF age = (47.33..54.0] AND sex = 1 AND cp = 1 AND trestbps = (123.0..134.0] AND chol = (192.17..219.33] AND fbs = 0 AND restecg = 1 AND thalach = (146.0..161.0] AND exang = 0 AND oldpeak = (0.65..1.3] AND slope = 2 AND ca = 1 AND thal = 2 THEN target = 1": {
            "status": true,
            "expl": [
                "age",
                "cp",
                "trestbps"
            ],
            "minsize": 3,
            "exprtime": 589.2999999999997
        },
        "IF age = (47.33..54.0] AND sex = 1 AND cp = 1 AND trestbps = (164.0..+inf) AND chol = (272.33..306.83] AND fbs = 0 AND restecg = 0 AND thalach = (177.0..+inf) AND exang = 0 AND oldpeak = (-inf..0.65] AND slope = 2 AND ca = 1 AND thal = 3 THEN target = 1": {
            "status": true,
            "expl": [
                "thalach",
                "oldpeak"
            ],
            "minsize": 2,
            "exprtime": 75.07100000000122
        },
        "IF age = (47.33..54.0] AND sex = 1 AND cp = 2 AND trestbps = (110.0..123.0] AND chol = (-inf..192.17] AND fbs = 0 AND restecg = 0 AND thalach = (114.0..130.0] AND exang = 0 AND oldpeak = (0.65..1.3] AND slope = 2 AND ca = 3 AND thal = 2 THEN target = 1": {
            "status": true,
            "expl": [
                "cp",
                "thal",
                "exang",
                "age"
            ],
            "minsize": 4,
            "exprtime": 293.7840000000005
        },
        "IF age = (47.33..54.0] AND sex = 1 AND cp = 2 AND trestbps = (123.0..134.0] AND chol = (219.33..245.5] AND fbs = 1 AND restecg = 0 AND thalach = (161.0..177.0] AND exang = 0 AND oldpeak = (2.05..2.8] AND slope = 1 AND ca = 0 AND thal = 2 THEN target = 0": {
            "status": true,
            "expl": [
                "oldpeak",
                "age",
                "thalach"
            ],
            "minsize": 3,
            "exprtime": 189.32999999999998
        },
        "IF age = (47.33..54.0] AND sex = 1 AND cp = 3 AND trestbps = (110.0..123.0] AND chol = (-inf..192.17] AND fbs = 0 AND restecg = 0 AND thalach = (177.0..+inf) AND exang = 0 AND oldpeak = (-inf..0.65] AND slope = 1 AND ca = 0 AND thal = 1 THEN target = 1": {
            "status": true,
            "expl": [
                "thalach"
            ],
            "minsize": 1,
            "exprtime": 67.45700000000099
        },
        "IF age = (54.0..60.67] AND sex = 0 AND cp = 0 AND trestbps = (-inf..110.0] AND chol = (245.5..272.33] AND fbs = 0 AND restecg = 0 AND thalach = (114.0..130.0] AND exang = 0 AND oldpeak = (0.65..1.3] AND slope = 1 AND ca = 0 AND thal = 2 THEN target = 0": {
            "status": true,
            "expl": [
                "cp",
                "thalach",
                "age"
            ],
            "minsize": 3,
            "exprtime": 432.75799999999975
        },
        "IF age = (54.0..60.67] AND sex = 0 AND cp = 0 AND trestbps = (110.0..123.0] AND chol = (306.83..+inf) AND fbs = 0 AND restecg = 1 AND thalach = (161.0..177.0] AND exang = 1 AND oldpeak = (-inf..0.65] AND slope = 2 AND ca = 0 AND thal = 2 THEN target = 1": {
            "status": true,
            "expl": [
                "ca",
                "thal",
                "slope",
                "trestbps"
            ],
            "minsize": 4,
            "exprtime": 432.1589999999986
        },
        "IF age = (54.0..60.67] AND sex = 0 AND cp = 0 AND trestbps = (123.0..134.0] AND chol = (306.83..+inf) AND fbs = 0 AND restecg = 0 AND thalach = (146.0..161.0] AND exang = 1 AND oldpeak = (1.3..2.05] AND slope = 1 AND ca = 2 AND thal = 3 THEN target = 0": {
            "status": true,
            "expl": [
                "ca",
                "age"
            ],
            "minsize": 2,
            "exprtime": 232.98699999999963
        },
        "IF age = (54.0..60.67] AND sex = 0 AND cp = 0 AND trestbps = (134.0..146.0] AND chol = (219.33..245.5] AND fbs = 0 AND restecg = 1 AND thalach = (114.0..130.0] AND exang = 1 AND oldpeak = (-inf..0.65] AND slope = 1 AND ca = 0 AND thal = 3 THEN target = 0": {
            "status": true,
            "expl": [
                "cp",
                "thal",
                "thalach"
            ],
            "minsize": 3,
            "exprtime": 401.83399999999915
        },
        "IF age = (54.0..60.67] AND sex = 0 AND cp = 0 AND trestbps = (164.0..+inf) AND chol = (245.5..272.33] AND fbs = 0 AND restecg = 1 AND thalach = (130.0..146.0] AND exang = 1 AND oldpeak = (-inf..0.65] AND slope = 1 AND ca = 0 AND thal = 2 THEN target = 1": {
            "status": true,
            "expl": [
                "trestbps",
                "oldpeak",
                "restecg"
            ],
            "minsize": 3,
            "exprtime": 247.3150000000004
        },
        "IF age = (54.0..60.67] AND sex = 0 AND cp = 0 AND trestbps = (164.0..+inf) AND chol = (272.33..306.83] AND fbs = 1 AND restecg = 0 AND thalach = (130.0..146.0] AND exang = 1 AND oldpeak = (3.55..+inf) AND slope = 0 AND ca = 2 AND thal = 3 THEN target = 0": {
            "status": true,
            "expl": [
                "oldpeak"
            ],
            "minsize": 1,
            "exprtime": 82.83999999999914
        },
        "IF age = (54.0..60.67] AND sex = 0 AND cp = 0 AND trestbps = (164.0..+inf) AND chol = (306.83..+inf) AND fbs = 0 AND restecg = 2 AND thalach = (114.0..130.0] AND exang = 1 AND oldpeak = (2.8..3.55] AND slope = 1 AND ca = 0 AND thal = 2 THEN target = 0": {
            "status": true,
            "expl": [
                "oldpeak",
                "age",
                "thalach"
            ],
            "minsize": 3,
            "exprtime": 165.70299999999884
        },
        "IF age = (54.0..60.67] AND sex = 0 AND cp = 1 AND trestbps = (134.0..146.0] AND chol = (272.33..306.83] AND fbs = 0 AND restecg = 0 AND thalach = (146.0..161.0] AND exang = 0 AND oldpeak = (0.65..1.3] AND slope = 1 AND ca = 0 AND thal = 2 THEN target = 1": {
            "status": true,
            "expl": [
                "sex",
                "thal",
                "ca",
                "cp"
            ],
            "minsize": 4,
            "exprtime": 395.84200000000004
        },
        "IF age = (54.0..60.67] AND sex = 1 AND cp = 0 AND trestbps = (-inf..110.0] AND chol = (192.17..219.33] AND fbs = 0 AND restecg = 1 AND thalach = (114.0..130.0] AND exang = 1 AND oldpeak = (1.3..2.05] AND slope = 1 AND ca = 0 AND thal = 1 THEN target = 0": {
            "status": true,
            "expl": [
                "cp",
                "exang",
                "sex",
                "thalach"
            ],
            "minsize": 4,
            "exprtime": 709.3050000000005
        },
        "IF age = (54.0..60.67] AND sex = 1 AND cp = 0 AND trestbps = (123.0..134.0] AND chol = (-inf..192.17] AND fbs = 0 AND restecg = 0 AND thalach = (-inf..114.0] AND exang = 1 AND oldpeak = (2.05..2.8] AND slope = 1 AND ca = 1 AND thal = 1 THEN target = 0": {
            "status": true,
            "expl": [
                "oldpeak",
                "cp"
            ],
            "minsize": 2,
            "exprtime": 188.9699999999994
        },
        "IF age = (54.0..60.67] AND sex = 1 AND cp = 0 AND trestbps = (134.0..146.0] AND chol = (192.17..219.33] AND fbs = 0 AND restecg = 1 AND thalach = (-inf..114.0] AND exang = 0 AND oldpeak = (1.3..2.05] AND slope = 1 AND ca = 1 AND thal = 3 THEN target = 0": {
            "status": true,
            "expl": [
                "thalach",
                "cp",
                "age"
            ],
            "minsize": 3,
            "exprtime": 237.5329999999991
        },
        "IF age = (54.0..60.67] AND sex = 1 AND cp = 0 AND trestbps = (134.0..146.0] AND chol = (272.33..306.83] AND fbs = 0 AND restecg = 0 AND thalach = (130.0..146.0] AND exang = 1 AND oldpeak = (2.05..2.8] AND slope = 1 AND ca = 2 AND thal = 3 THEN target = 0": {
            "status": true,
            "expl": [
                "oldpeak",
                "cp",
                "exang"
            ],
            "minsize": 3,
            "exprtime": 192.1210000000002
        },
        "IF age = (54.0..60.67] AND sex = 1 AND cp = 0 AND trestbps = (134.0..146.0] AND chol = (272.33..306.83] AND fbs = 0 AND restecg = 0 AND thalach = (161.0..177.0] AND exang = 0 AND oldpeak = (0.65..1.3] AND slope = 1 AND ca = 2 AND thal = 3 THEN target = 0": {
            "status": true,
            "expl": [
                "ca",
                "age"
            ],
            "minsize": 2,
            "exprtime": 217.74499999999898
        },
        "IF age = (54.0..60.67] AND sex = 1 AND cp = 0 AND trestbps = (146.0..164.0] AND chol = (272.33..306.83] AND fbs = 0 AND restecg = 1 AND thalach = (-inf..114.0] AND exang = 1 AND oldpeak = (0.65..1.3] AND slope = 1 AND ca = 1 AND thal = 3 THEN target = 0": {
            "status": true,
            "expl": [
                "thalach",
                "age",
                "cp"
            ],
            "minsize": 3,
            "exprtime": 265.57299999999987
        },
        "IF age = (54.0..60.67] AND sex = 1 AND cp = 0 AND trestbps = (164.0..+inf) AND chol = (272.33..306.83] AND fbs = 1 AND restecg = 0 AND thalach = (114.0..130.0] AND exang = 0 AND oldpeak = (0.65..1.3] AND slope = 1 AND ca = 3 AND thal = 3 THEN target = 0": {
            "status": true,
            "expl": [
                "cp",
                "thal",
                "thalach"
            ],
            "minsize": 3,
            "exprtime": 476.5859999999993
        },
        "IF age = (54.0..60.67] AND sex = 1 AND cp = 1 AND trestbps = (110.0..123.0] AND chol = (219.33..245.5] AND fbs = 0 AND restecg = 1 AND thalach = (161.0..177.0] AND exang = 0 AND oldpeak = (-inf..0.65] AND slope = 0 AND ca = 0 AND thal = 2 THEN target = 0": {
            "status": true,
            "expl": [
                "slope",
                "cp",
                "thalach"
            ],
            "minsize": 3,
            "exprtime": 226.2170000000019
        },
        "IF age = (54.0..60.67] AND sex = 1 AND cp = 1 AND trestbps = (123.0..134.0] AND chol = (219.33..245.5] AND fbs = 0 AND restecg = 1 AND thalach = (130.0..146.0] AND exang = 0 AND oldpeak = (-inf..0.65] AND slope = 1 AND ca = 4 AND thal = 3 THEN target = 1": {
            "status": true,
            "expl": [
                "ca",
                "oldpeak"
            ],
            "minsize": 2,
            "exprtime": 141.59199999999927
        },
        "IF age = (54.0..60.67] AND sex = 1 AND cp = 1 AND trestbps = (123.0..134.0] AND chol = (245.5..272.33] AND fbs = 0 AND restecg = 1 AND thalach = (146.0..161.0] AND exang = 0 AND oldpeak = (-inf..0.65] AND slope = 2 AND ca = 0 AND thal = 2 THEN target = 0": {
            "status": true,
            "expl": [
                "sex",
                "age",
                "chol",
                "trestbps",
                "cp",
                "thalach"
            ],
            "minsize": 6,
            "exprtime": 768.2059999999992
        },
        "IF age = (54.0..60.67] AND sex = 1 AND cp = 2 AND trestbps = (134.0..146.0] AND chol = (-inf..192.17] AND fbs = 0 AND restecg = 0 AND thalach = (146.0..161.0] AND exang = 0 AND oldpeak = (2.8..3.55] AND slope = 1 AND ca = 0 AND thal = 2 THEN target = 0": {
            "status": true,
            "expl": [
                "oldpeak",
                "age"
            ],
            "minsize": 2,
            "exprtime": 142.39900000000105
        },
        "IF age = (54.0..60.67] AND sex = 1 AND cp = 3 AND trestbps = (110.0..123.0] AND chol = (192.17..219.33] AND fbs = 0 AND restecg = 0 AND thalach = (161.0..177.0] AND exang = 0 AND oldpeak = (1.3..2.05] AND slope = 1 AND ca = 0 AND thal = 3 THEN target = 1": {
            "status": true,
            "expl": [
                "cp",
                "ca",
                "thalach"
            ],
            "minsize": 3,
            "exprtime": 224.02100000000047
        },
        "IF age = (54.0..60.67] AND sex = 1 AND cp = 3 AND trestbps = (164.0..+inf) AND chol = (245.5..272.33] AND fbs = 0 AND restecg = 0 AND thalach = (130.0..146.0] AND exang = 0 AND oldpeak = (3.55..+inf) AND slope = 0 AND ca = 0 AND thal = 3 THEN target = 0": {
            "status": true,
            "expl": [
                "oldpeak"
            ],
            "minsize": 1,
            "exprtime": 44.019999999999726
        },
        "IF age = (54.0..60.67] AND sex = 1 AND cp = 3 AND trestbps = (164.0..+inf) AND chol = (272.33..306.83] AND fbs = 0 AND restecg = 0 AND thalach = (146.0..161.0] AND exang = 0 AND oldpeak = (-inf..0.65] AND slope = 1 AND ca = 0 AND thal = 3 THEN target = 1": {
            "status": true,
            "expl": [
                "cp",
                "ca",
                "oldpeak"
            ],
            "minsize": 3,
            "exprtime": 187.50599999999906
        },
        "IF age = (60.67..67.33] AND sex = 0 AND cp = 0 AND trestbps = (146.0..164.0] AND chol = (-inf..192.17] AND fbs = 0 AND restecg = 0 AND thalach = (130.0..146.0] AND exang = 0 AND oldpeak = (3.55..+inf) AND slope = 0 AND ca = 3 AND thal = 3 THEN target = 0": {
            "status": true,
            "expl": [
                "oldpeak"
            ],
            "minsize": 1,
            "exprtime": 80.82500000000081
        },
        "IF age = (60.67..67.33] AND sex = 0 AND cp = 2 AND trestbps = (134.0..146.0] AND chol = (245.5..272.33] AND fbs = 0 AND restecg = 0 AND thalach = (161.0..177.0] AND exang = 0 AND oldpeak = (-inf..0.65] AND slope = 2 AND ca = 0 AND thal = 2 THEN target = 1": {
            "status": true,
            "expl": [
                "cp",
                "sex",
                "ca"
            ],
            "minsize": 3,
            "exprtime": 352.58799999999724
        },
        "IF age = (60.67..67.33] AND sex = 1 AND cp = 0 AND trestbps = (134.0..146.0] AND chol = (-inf..192.17] AND fbs = 0 AND restecg = 0 AND thalach = (130.0..146.0] AND exang = 1 AND oldpeak = (3.55..+inf) AND slope = 2 AND ca = 2 AND thal = 3 THEN target = 0": {
            "status": true,
            "expl": [
                "oldpeak"
            ],
            "minsize": 1,
            "exprtime": 49.68399999999917
        },
        "IF age = (60.67..67.33] AND sex = 1 AND cp = 0 AND trestbps = (134.0..146.0] AND chol = (192.17..219.33] AND fbs = 0 AND restecg = 0 AND thalach = (130.0..146.0] AND exang = 0 AND oldpeak = (1.3..2.05] AND slope = 1 AND ca = 2 AND thal = 1 THEN target = 0": {
            "status": true,
            "expl": [
                "ca",
                "thal"
            ],
            "minsize": 2,
            "exprtime": 212.1840000000006
        },
        "IF age = (60.67..67.33] AND sex = 1 AND cp = 0 AND trestbps = (134.0..146.0] AND chol = (192.17..219.33] AND fbs = 0 AND restecg = 0 AND thalach = (130.0..146.0] AND exang = 1 AND oldpeak = (1.3..2.05] AND slope = 2 AND ca = 1 AND thal = 3 THEN target = 0": {
            "status": true,
            "expl": [
                "cp",
                "ca",
                "thalach"
            ],
            "minsize": 3,
            "exprtime": 430.08199999999874
        },
        "IF age = (60.67..67.33] AND sex = 1 AND cp = 3 AND trestbps = (164.0..+inf) AND chol = (219.33..245.5] AND fbs = 0 AND restecg = 0 AND thalach = (146.0..161.0] AND exang = 0 AND oldpeak = (-inf..0.65] AND slope = 1 AND ca = 0 AND thal = 3 THEN target = 1": {
            "status": true,
            "expl": [
                "cp",
                "ca",
                "age"
            ],
            "minsize": 3,
            "exprtime": 175.4269999999991
        },
        "IF age = (67.33..+inf) AND sex = 0 AND cp = 3 AND trestbps = (134.0..146.0] AND chol = (219.33..245.5] AND fbs = 0 AND restecg = 1 AND thalach = (146.0..161.0] AND exang = 0 AND oldpeak = (1.3..2.05] AND slope = 2 AND ca = 2 AND thal = 2 THEN target = 1": {
            "status": true,
            "expl": [
                "cp",
                "thal",
                "oldpeak",
                "age",
                "sex"
            ],
            "minsize": 5,
            "exprtime": 323.7050000000004
        },
        "IF age = (67.33..+inf) AND sex = 1 AND cp = 1 AND trestbps = (146.0..164.0] AND chol = (219.33..245.5] AND fbs = 0 AND restecg = 0 AND thalach = (130.0..146.0] AND exang = 0 AND oldpeak = (-inf..0.65] AND slope = 2 AND ca = 0 AND thal = 2 THEN target = 0": {
            "status": true,
            "expl": [
                "age",
                "sex",
                "thalach",
                "cp"
            ],
            "minsize": 4,
            "exprtime": 291.7740000000002
        },
        "IF age = (67.33..+inf) AND sex = 1 AND cp = 2 AND trestbps = (110.0..123.0] AND chol = (272.33..306.83] AND fbs = 0 AND restecg = 1 AND thalach = (146.0..161.0] AND exang = 0 AND oldpeak = (0.65..1.3] AND slope = 2 AND ca = 1 AND thal = 3 THEN target = 0": {
            "status": true,
            "expl": [
                "age",
                "thal",
                "sex"
            ],
            "minsize": 3,
            "exprtime": 306.26900000000035
        }
    }
}